vis_package/__init__.py
vis_package/complete_method.py
vis_package/feature_selection.py
vis_package/method_test.py
vis_package/power_method.py
vis_package/sinhF.py
vis_package/vis_method.py
vis_package-1.0.16.dist-info/METADATA
vis_package-1.0.16.dist-info/WHEEL
vis_package-1.0.16.dist-info/top_level.txt
vis_package-1.0.16.dist-info/RECORD
